odoo10_addon_mrp_production_hierarchy-10.0.1.0.0.99.dev15-py3.8-nspkg.pth
odoo/addons/mrp_production_hierarchy/README.rst
odoo/addons/mrp_production_hierarchy/__init__.py
odoo/addons/mrp_production_hierarchy/__manifest__.py
odoo/addons/mrp_production_hierarchy/i18n/fr.po
odoo/addons/mrp_production_hierarchy/i18n/mrp_production_hierarchy.pot
odoo/addons/mrp_production_hierarchy/models/__init__.py
odoo/addons/mrp_production_hierarchy/models/mrp_production.py
odoo/addons/mrp_production_hierarchy/models/procurement_order.py
odoo/addons/mrp_production_hierarchy/readme/CONTRIBUTORS.rst
odoo/addons/mrp_production_hierarchy/readme/DESCRIPTION.rst
odoo/addons/mrp_production_hierarchy/readme/ROADMAP.rst
odoo/addons/mrp_production_hierarchy/readme/USAGE.rst
odoo/addons/mrp_production_hierarchy/static/description/icon.png
odoo/addons/mrp_production_hierarchy/static/description/index.html
odoo/addons/mrp_production_hierarchy/static/description/mrp_production_hierarchy_1.png
odoo/addons/mrp_production_hierarchy/static/description/mrp_production_hierarchy_2.png
odoo/addons/mrp_production_hierarchy/static/description/mrp_production_hierarchy_3.png
odoo/addons/mrp_production_hierarchy/tests/__init__.py
odoo/addons/mrp_production_hierarchy/tests/test_mrp_production_hierarchy.py
odoo/addons/mrp_production_hierarchy/views/mrp_production.xml
odoo10_addon_mrp_production_hierarchy-10.0.1.0.0.99.dev15.dist-info/METADATA
odoo10_addon_mrp_production_hierarchy-10.0.1.0.0.99.dev15.dist-info/WHEEL
odoo10_addon_mrp_production_hierarchy-10.0.1.0.0.99.dev15.dist-info/namespace_packages.txt
odoo10_addon_mrp_production_hierarchy-10.0.1.0.0.99.dev15.dist-info/top_level.txt
odoo10_addon_mrp_production_hierarchy-10.0.1.0.0.99.dev15.dist-info/RECORD
